CHANGES.txt
MANIFEST.in
README.md
TODO
setup.py
djinn_i18n/__init__.py
djinn_i18n/__init__.pyc
djinn_i18n/models.py
djinn_i18n/models.pyc
djinn_i18n/po.py
djinn_i18n/po.pyc
djinn_i18n/tool.py
djinn_i18n/tool.pyc
djinn_i18n/urls.py
djinn_i18n/urls.pyc
djinn_i18n/utils.py
djinn_i18n/utils.pyc
djinn_i18n.egg-info/PKG-INFO
djinn_i18n.egg-info/SOURCES.txt
djinn_i18n.egg-info/dependency_links.txt
djinn_i18n.egg-info/entry_points.txt
djinn_i18n.egg-info/not-zip-safe
djinn_i18n.egg-info/requires.txt
djinn_i18n.egg-info/top_level.txt
djinn_i18n/.idea/djinn_i18n.iml
djinn_i18n/.idea/encodings.xml
djinn_i18n/.idea/misc.xml
djinn_i18n/.idea/modules.xml
djinn_i18n/.idea/vcs.xml
djinn_i18n/.idea/workspace.xml
djinn_i18n/.idea/scopes/scope_settings.xml
djinn_i18n/static/css/djinn_i18n.css
djinn_i18n/static/js/djinn_i18n.js
djinn_i18n/templates/djinn_i18n/index.html
djinn_i18n/templates/djinn_i18n/modaltrans.html
djinn_i18n/templates/djinn_i18n/module.html
djinn_i18n/templates/djinn_i18n/search.html
djinn_i18n/templates/djinn_i18n/trans.html
djinn_i18n/templates/djinn_i18n/snippets/entry.html
djinn_i18n/templates/djinn_i18n/snippets/searchform.html
djinn_i18n/templatetags/__init__.py
djinn_i18n/templatetags/__init__.pyc
djinn_i18n/templatetags/djinn_i18n_tags.py
djinn_i18n/templatetags/djinn_i18n_tags.pyc
djinn_i18n/views/__init__.py
djinn_i18n/views/__init__.pyc
djinn_i18n/views/index.py
djinn_i18n/views/index.pyc
djinn_i18n/views/module.py
djinn_i18n/views/module.pyc
djinn_i18n/views/po.py
djinn_i18n/views/po.pyc
djinn_i18n/views/reload.py
djinn_i18n/views/reload.pyc
djinn_i18n/views/trans.py
djinn_i18n/views/trans.pyc