Metadata-Version: 1.1
Name: djinn-i18n
Version: 1.0.5
Summary: Djinn i18n
Home-page: https://github.com/PythonUnited/djinn-i18n
Author: PythonUnited
Author-email: info@pythonunited.com
License: beer-ware
Keywords: Djinn i18n
Platform: UNKNOWN
Classifier: Development Status :: 3 - Alpha
Classifier: Framework :: Django
Classifier: Intended Audience :: Developers
Classifier: License :: Freely Distributable
Classifier: Programming Language :: Python
Classifier: Topic :: Internet :: WWW/HTTP :: Site Management
Classifier: Topic :: Software Development :: Libraries :: Application Frameworks
